LICENSE
MANIFEST.in
README.md
setup.py
cronus/__init__.py
cronus/__main__.py
cronus/cmdb.py
cronus/configure.py
cronus/event.py
cronus/incident.py
cronus/now.py
cronus/profile.py
cronus/properties.py
nowcli.egg-info/PKG-INFO
nowcli.egg-info/SOURCES.txt
nowcli.egg-info/dependency_links.txt
nowcli.egg-info/entry_points.txt
nowcli.egg-info/not-zip-safe
nowcli.egg-info/requires.txt
nowcli.egg-info/top_level.txt