Metadata-Version: 2.1
Name: nowcli
Version: 1.0.1
Summary: UNKNOWN
Home-page: https://github.com/advlab/cronus
Author: Anthony Angelo
Author-email: anthony.angelo@servicenow.com
License: License :: OSI Approved :: MIT License
Platform: UNKNOWN
Classifier: Programming Language :: Python :: 3
Requires-Python: >=3.6
